Metadata-Version: 2.1
Name: brainlit
Version: 0.3.6
Summary: Code to process and analyze brainlit data
Home-page: https://github.com/neurodata/brainlit
Author: ('Thomas Athey, Bijan Varjivand, Ryan Lu, Matt Figdore, Alex Fiallos, Stanley Wang, Victor Wang',)
Author-email: tathey1@jhu.edu
License: Apache License 2.0
Classifier: Development Status :: 3 - Alpha
Classifier: Intended Audience :: Science/Research
Classifier: Topic :: Scientific/Engineering :: Mathematics
Classifier: License :: OSI Approved :: Apache Software License
Classifier: Programming Language :: Python :: 3
Classifier: Programming Language :: Python :: 3.5
Classifier: Programming Language :: Python :: 3.6
Classifier: Programming Language :: Python :: 3.7
License-File: LICENSE
Requires-Dist: numpy (==1.23.2)
Requires-Dist: CloudReg
Requires-Dist: aicspylibczi (>=3.0.5)
Requires-Dist: brainrender
Requires-Dist: numpy (>=1.8.1)
Requires-Dist: scikit-image (>=0.16.2)
Requires-Dist: networkx (>=2.1)
Requires-Dist: scikit-learn (==1.1.2)
Requires-Dist: scipy (>=1.1.0)
Requires-Dist: seaborn (>=0.12.2)
Requires-Dist: tifffile (>=2020.7.17)
Requires-Dist: napari[pyqt5] (>=0.2.11)
Requires-Dist: PyQt5 (<=5.15.7)
Requires-Dist: cloud-volume (>=4.2.0)
Requires-Dist: feather-format (==0.4.1)
Requires-Dist: ome-zarr (>=0.6.0)
Requires-Dist: zarr (>=2.10.2)
Requires-Dist: h5py (>=3.3.0)
Requires-Dist: similaritymeasures (>=0.4.4)
Requires-Dist: statannotations (>=0.4.4)
Requires-Dist: igneous-pipeline
